cleanlab_cli/__init__.py
cleanlab_cli/api_service.py
cleanlab_cli/click_helpers.py
cleanlab_cli/main.py
cleanlab_cli/settings.py
cleanlab_cli/types.py
cleanlab_cli/util.py
cleanlab_cli/version.py
cleanlab_cli/classes/__init__.py
cleanlab_cli/classes/csv_dataset.py
cleanlab_cli/classes/dataset.py
cleanlab_cli/classes/excel_dataset.py
cleanlab_cli/classes/json_dataset.py
cleanlab_cli/cleanset/__init__.py
cleanlab_cli/cleanset/commands.py
cleanlab_cli/cleanset/download.py
cleanlab_cli/cleanset/download_helpers.py
cleanlab_cli/dataset/__init__.py
cleanlab_cli/dataset/commands.py
cleanlab_cli/dataset/helpers.py
cleanlab_cli/dataset/image_utils.py
cleanlab_cli/dataset/schema.py
cleanlab_cli/dataset/schema_helpers.py
cleanlab_cli/dataset/schema_types.py
cleanlab_cli/dataset/upload.py
cleanlab_cli/dataset/upload_helpers.py
cleanlab_cli/dataset/upload_types.py
cleanlab_cli/decorators/__init__.py
cleanlab_cli/decorators/auth_config.py
cleanlab_cli/decorators/previous_state.py
cleanlab_cli/login/__init__.py
cleanlab_cli/login/login.py
tests/__init__.py
tests/bench.py
tests/commands/__init__.py
tests/commands/test_schema.py
cleanlab_cli-0.1.14.dist-info/LICENSE
cleanlab_cli-0.1.14.dist-info/METADATA
cleanlab_cli-0.1.14.dist-info/WHEEL
cleanlab_cli-0.1.14.dist-info/entry_points.txt
cleanlab_cli-0.1.14.dist-info/top_level.txt
cleanlab_cli-0.1.14.dist-info/RECORD
